how_long/__init__.py
how_long/how_long.py
how_long-0.1.2.dist-info/LICENSE
how_long-0.1.2.dist-info/WHEEL
how_long-0.1.2.dist-info/METADATA
how_long-0.1.2.dist-info/RECORD
